odoo/addons/connector_search_engine_serializer_ir_export/README.rst
odoo/addons/connector_search_engine_serializer_ir_export/__init__.py
odoo/addons/connector_search_engine_serializer_ir_export/__manifest__.py
odoo/addons/connector_search_engine_serializer_ir_export/i18n/connector_search_engine_serializer_ir_export.pot
odoo/addons/connector_search_engine_serializer_ir_export/i18n/it.po
odoo/addons/connector_search_engine_serializer_ir_export/models/__init__.py
odoo/addons/connector_search_engine_serializer_ir_export/models/se_index.py
odoo/addons/connector_search_engine_serializer_ir_export/readme/CONTRIBUTORS.rst
odoo/addons/connector_search_engine_serializer_ir_export/readme/DESCRIPTION.rst
odoo/addons/connector_search_engine_serializer_ir_export/static/description/icon.png
odoo/addons/connector_search_engine_serializer_ir_export/static/description/index.html
odoo/addons/connector_search_engine_serializer_ir_export/tests/__init__.py
odoo/addons/connector_search_engine_serializer_ir_export/tests/test_serializer.py
odoo/addons/connector_search_engine_serializer_ir_export/tests/fixtures/ir_exports_test.xml
odoo/addons/connector_search_engine_serializer_ir_export/tools/__init__.py
odoo/addons/connector_search_engine_serializer_ir_export/tools/serializer.py
odoo/addons/connector_search_engine_serializer_ir_export/views/se_index_view.xml
odoo_addon_connector_search_engine_serializer_ir_export-16.0.1.0.2.6.dist-info/METADATA
odoo_addon_connector_search_engine_serializer_ir_export-16.0.1.0.2.6.dist-info/WHEEL
odoo_addon_connector_search_engine_serializer_ir_export-16.0.1.0.2.6.dist-info/top_level.txt
odoo_addon_connector_search_engine_serializer_ir_export-16.0.1.0.2.6.dist-info/RECORD
