Metadata-Version: 2.1
Name: odoo-addon-connector-search-engine-serializer-ir-export
Version: 16.0.1.0.2.6
Summary: Use Exporter (ir.exports) as serializer for index
Home-page: https://github.com/OCA/search-engine
Author: Akretion, Odoo Community Association (OCA)
Author-email: support@odoo-community.org
License: AGPL-3
Platform: UNKNOWN
Classifier: Programming Language :: Python
Classifier: Framework :: Odoo
Classifier: Framework :: Odoo :: 16.0
Classifier: License :: OSI Approved :: GNU Affero General Public License v3
Classifier: Development Status :: 3 - Alpha
Requires-Python: >=3.10
Requires-Dist: odoo-addon-connector-search-engine <16.1dev,>=16.0dev
Requires-Dist: odoo-addon-jsonifier <16.1dev,>=16.0dev
Requires-Dist: odoo <16.1dev,>=16.0a
